{
    "name": "Introduction to Docker",
    "description": "Introduction to Docker Course Materials",
    "training_version": "1.0.0",
    "protected": ["presenter", "onepage"],
    "user": "docker",
    "password": "maersk",
    "issues": "https://github.com/dotcloud/docker-fundamentals",
    "favicon": "https://www.docker.io/static/favicon.png",
    "sections": [

        "Course_Overview/Cover.md",
        "Course_Overview/Objectives.md",
        "Course_Overview/Body.md",

        "About_Docker/Cover.md",
        "About_Docker/Objectives.md",
        "About_Docker/Body.md",

        "Instant_Gratification/Cover.md",
        "Instant_Gratification/Objectives.md",
        "Instant_Gratification/Body.md",

        "Install_Docker/Cover.md",
        "Install_Docker/Objectives.md",
        "Install_Docker/Body.md",

        "Docker_Hub/Cover.md",
        "Docker_Hub/Objectives.md",
        "Docker_Hub/Body.md",

        "Initial_Images/Cover.md",
        "Initial_Images/Objectives.md",
        "Initial_Images/Body.md",

        "Own_Container/Cover.md",
        "Own_Container/Objectives.md",
        "Own_Container/Body.md",

        "Building_Images_Interactively/Cover.md",
        "Building_Images_Interactively/Objectives.md",
        "Building_Images_Interactively/Body.md",

        "Building_Images_With_Dockerfiles/Cover.md",
        "Building_Images_With_Dockerfiles/Objectives.md",
        "Building_Images_With_Dockerfiles/Body.md",

        "Working_With_Images/Cover.md",
        "Working_With_Images/Objectives.md",
        "Working_With_Images/Body.md",

        "Local_Development_Workflow/Cover.md",
        "Local_Development_Workflow/Objectives.md",
        "Local_Development_Workflow/Body.md",

        "Container_Networking_Basics/Cover.md",
        "Container_Networking_Basics/Objectives.md",
        "Container_Networking_Basics/Body.md",

        "Working_With_Volumes/Cover.md",
        "Working_With_Volumes/Objectives.md",
        "Working_With_Volumes/Body.md",

        "Connecting_Containers/Cover.md",
        "Connecting_Containers/Objectives.md",
        "Connecting_Containers/Body.md",

        "Orchestration/Cover.md",
        "Orchestration/Objectives.md",
        "Orchestration/Body.md",

        "Ambassadors/Cover.md",
        "Ambassadors/Objectives.md",
        "Ambassadors/Body.md",

        "Testing_Workflow/Cover.md",
        "Testing_Workflow/Objectives.md",
        "Testing_Workflow/Body.md",

        "Security/Cover.md",
        "Security/Objectives.md",
        "Security/Body.md",
        "Security/Summary.md",

        "Securing_With_TLS/Cover.md",
        "Securing_With_TLS/Objectives.md",
        "Securing_With_TLS/Body.md",

        "Docker_API/Cover.md",
        "Docker_API/Objectives.md",
        "Docker_API/Body.md",

        "Course_Conclusion/Cover.md",
        "Course_Conclusion/Body.md"
    ]
}
